geoentropy/__init__.py
geoentropy/batty.py
geoentropy/csv_to_matrix.py
geoentropy/karlstrom.py
geoentropy/leibovici.py
geoentropy/oneill.py
geoentropy/shannon.py
geoentropy/shannon_z.py
geoentropy/spatial_partition.py
GeoEntropy-0.2.0.dist-info/LICENSE
GeoEntropy-0.2.0.dist-info/METADATA
GeoEntropy-0.2.0.dist-info/WHEEL
GeoEntropy-0.2.0.dist-info/top_level.txt
GeoEntropy-0.2.0.dist-info/RECORD
