Metadata-Version: 2.1
Name: GeoEntropy
Version: 0.2.0
Summary: A Python package for computing geometric/spatial entropy metrics for data in matrix format.
Home-page: https://github.com/maxkryschi/geoentropy
Author: Max Kryschi
Author-email: 
License: MIT License
Classifier: Programming Language :: Python :: 3
Classifier: License :: OSI Approved :: MIT License
Classifier: Operating System :: OS Independent
Requires-Python: >=3.9
License-File: LICENSE
Requires-Dist: numpy
Requires-Dist: pandas
Requires-Dist: matplotlib
Requires-Dist: scipy
Requires-Dist: shapely
